renamerename/__init__.py
renamerename/__main__.py
renamerename/executor/__init__.py
renamerename/executor/app.py
renamerename/executor/encoder_decoder.py
renamerename/executor/executor.py
renamerename/handlers/__init__.py
renamerename/handlers/filetransformation.py
renamerename/handlers/handlers.py
renamerename/tests/__init__.py
renamerename/tests/test_app.py
renamerename/tests/test_encoder_decoder.py
renamerename/tests/test_executor.py
renamerename/tests/test_filelisthandler.py
renamerename/tests/test_filenamehandler.py
renamerename/tests/test_filetransformation.py
renamerename-1.0.0.dist-info/LICENSE
renamerename-1.0.0.dist-info/METADATA
renamerename-1.0.0.dist-info/WHEEL
renamerename-1.0.0.dist-info/entry_points.txt
renamerename-1.0.0.dist-info/top_level.txt
renamerename-1.0.0.dist-info/RECORD
