Metadata-Version: 2.1
Name: renamerename
Version: 1.0.0
Summary: Bulk renaming of files made easy
Home-page: https://github.com/mhmdkanj/RenameRename
Author: Mohamad Kanj
Author-email: mhmd.kanj@gmail.com
License: MIT
Platform: UNKNOWN
Classifier: License :: OSI Approved :: MIT License
Classifier: Programming Language :: Python :: 3
Classifier: Programming Language :: Python :: 3.6
Classifier: Topic :: System :: Filesystems
Classifier: Topic :: Desktop Environment :: File Managers
Requires-Python: >=3.6.0
